starrlib/__init__.py
starrlib/typed_bytes.py
starrlib-0.1.1.dist-info/LICENSE
starrlib-0.1.1.dist-info/METADATA
starrlib-0.1.1.dist-info/WHEEL
starrlib-0.1.1.dist-info/RECORD
